setup.py
distributions_udsnd/Binomialdistribution.py
distributions_udsnd/Gaussiandistribution.py
distributions_udsnd/Generaldistribution.py
distributions_udsnd/__init__.py
distributions_udsnd.egg-info/PKG-INFO
distributions_udsnd.egg-info/SOURCES.txt
distributions_udsnd.egg-info/dependency_links.txt
distributions_udsnd.egg-info/not-zip-safe
distributions_udsnd.egg-info/top_level.txt